tpds_extension/aes_message_encryption/extension.yaml
tpds_extension/aes_message_encryption/setup.py
tpds_extension/aes_message_encryption/version.py
tpds_extension/aes_message_encryption/backend/__init__.py
tpds_extension/aes_message_encryption/backend/api/__init__.py
tpds_extension/aes_message_encryption/backend/api/api.py
tpds_extension/aes_message_encryption/backend/api/model.py
tpds_extension/aes_message_encryption/backend/usecases/aes_message_encryption/aes_message_encryption.py
tpds_extension/aes_message_encryption/backend/usecases/aes_message_encryption/api.py
tpds_extension/aes_message_encryption/backend/usecases/proto_provision/__init__.py
tpds_extension/aes_message_encryption/backend/usecases/proto_provision/connect/__init__.py
tpds_extension/aes_message_encryption/backend/usecases/proto_provision/connect/connect.py
tpds_extension/aes_message_encryption/backend/usecases/proto_provision/helper/__init__.py
tpds_extension/aes_message_encryption/backend/usecases/proto_provision/helper/defines.py
tpds_extension/aes_message_encryption/backend/usecases/proto_provision/helper/helper.py
tpds_extension/aes_message_encryption/backend/usecases/proto_provision/helper/keys.py
tpds_extension/aes_message_encryption/backend/usecases/proto_provision/helper/utils.py
tpds_extension/aes_message_encryption/backend/usecases/proto_provision/symm_auth/__init__.py
tpds_extension/aes_message_encryption/backend/usecases/proto_provision/symm_auth/symm_auth.py
tpds_extension/aes_message_encryption/frontend/usecases/aes_message_encryption/firmware.zip
tpds_extension/aes_message_encryption/frontend/usecases/aes_message_encryption/info_aes_message_encryption.md
tpds_extension/aes_message_encryption/frontend/usecases/aes_message_encryption/readme.pdf
tpds_extension/aes_message_encryption/frontend/usecases/aes_message_encryption/td_aes_message_encryption.png
tpds_extension/aes_message_encryption/frontend/usecases/aes_message_encryption/usecase_config.yaml
tpds_extension_aes_message_encryption-1.1.1.dist-info/licenses/LICENSE
tpds_extension_aes_message_encryption-1.1.1.dist-info/METADATA
tpds_extension_aes_message_encryption-1.1.1.dist-info/WHEEL
tpds_extension_aes_message_encryption-1.1.1.dist-info/top_level.txt
tpds_extension_aes_message_encryption-1.1.1.dist-info/RECORD
