Metadata-Version: 2.4
Name: tpds-extension-aes-message-encryption
Version: 1.1.1
Summary: Microchip(SPG) Trust Platform - AES message encryption Usecase
Home-page: https://www.microchip.com/TrustPlatform
Author: Microchip Technology
Author-email: SPG.Tools@microchip.com
Classifier: License :: Other/Proprietary License
Classifier: Development Status :: 4 - Beta
Classifier: Programming Language :: Python :: 3
Classifier: Operating System :: OS Independent
Requires-Python: >=3.6
License-File: LICENSE
Dynamic: license-file
